{"Fixture":{"Id":571606,"Referee":"B. Millot","Timezone":"UTC","Date":"2020-12-12T17:00:00+01:00","Timestamp":1607788800,"Periods":{"First":1607788800,"Second":1607792400},"Venue":{"Id":667,"Name":"Orange V\u00E9lodrome","City":"Marseille"},"Status":{"Long":"Match Finished","Short":"FT","Elapsed":90}},"League":{"Id":61,"Name":"Ligue 1","Country":"France","Logo":"https://media.api-sports.io/football/leagues/61.png","Flag":"https://media.api-sports.io/flags/fr.svg","Season":2020,"Round":"Regular Season - 14"},"Teams":{"Home":{"Id":81,"Name":"Marseille","Logo":"https://media.api-sports.io/football/teams/81.png","Winner":true},"Away":{"Id":91,"Name":"Monaco","Logo":"https://media.api-sports.io/football/teams/91.png","Winner":false}},"Goals":{"Home":2,"Away":1},"Score":{"Halftime":{"Home":2,"Away":0},"Fulltime":{"Home":2,"Away":1},"Extratime":{"Home":null,"Away":null},"Penalty":{"Home":null,"Away":null}},"Events":[{"Time":{"Elapsed":5,"Extra":null},"Team":{"Id":81,"Name":"Marseille","Logo":"https://media.api-sports.io/football/teams/81.png"},"Player":{"Id":1922,"Name":"F. Thauvin"},"Assist":{"Id":2478,"Name":"D. Benedetto"},"Type":"Goal","Detail":"Normal Goal","Comments":null},{"Time":{"Elapsed":13,"Extra":null},"Team":{"Id":81,"Name":"Marseille","Logo":"https://media.api-sports.io/football/teams/81.png"},"Player":{"Id":2478,"Name":"D. Benedetto"},"Assist":{"Id":1922,"Name":"F. Thauvin"},"Type":"Goal","Detail":"Normal Goal","Comments":null},{"Time":{"Elapsed":24,"Extra":null},"Team":{"Id":81,"Name":"Marseille","Logo":"https://media.api-sports.io/football/teams/81.png"},"Player":{"Id":1914,"Name":"M. Sanson"},"Assist":{"Id":20696,"Name":"P. Gueye"},"Type":"subst","Detail":"Substitution 1","Comments":null},{"Time":{"Elapsed":43,"Extra":null},"Team":{"Id":91,"Name":"Monaco","Logo":"https://media.api-sports.io/football/teams/91.png"},"Player":{"Id":22254,"Name":"Youssouf Fofana"},"Assist":{"Id":null,"Name":null},"Type":"Card","Detail":"Yellow Card","Comments":"Foul"},{"Time":{"Elapsed":46,"Extra":null},"Team":{"Id":91,"Name":"Monaco","Logo":"https://media.api-sports.io/football/teams/91.png"},"Player":{"Id":95,"Name":"B. Badiashile"},"Assist":{"Id":2553,"Name":"G. Marip\u00E1n"},"Type":"subst","Detail":"Substitution 1","Comments":null},{"Time":{"Elapsed":52,"Extra":null},"Team":{"Id":91,"Name":"Monaco","Logo":"https://media.api-sports.io/football/teams/91.png"},"Player":{"Id":21998,"Name":"Axel Disasi"},"Assist":{"Id":null,"Name":null},"Type":"Var","Detail":"Goal cancelled","Comments":null},{"Time":{"Elapsed":58,"Extra":null},"Team":{"Id":91,"Name":"Monaco","Logo":"https://media.api-sports.io/football/teams/91.png"},"Player":{"Id":118,"Name":"Gelson Martins"},"Assist":{"Id":123,"Name":"P. Pellegri"},"Type":"subst","Detail":"Substitution 2","Comments":null},{"Time":{"Elapsed":58,"Extra":null},"Team":{"Id":91,"Name":"Monaco","Logo":"https://media.api-sports.io/football/teams/91.png"},"Player":{"Id":989,"Name":"K. Volland"},"Assist":{"Id":121,"Name":"S. Joveti\u0107"},"Type":"subst","Detail":"Substitution 3","Comments":null},{"Time":{"Elapsed":65,"Extra":null},"Team":{"Id":81,"Name":"Marseille","Logo":"https://media.api-sports.io/football/teams/81.png"},"Player":{"Id":25634,"Name":"M. Cuisance"},"Assist":{"Id":1918,"Name":"V. Germain"},"Type":"subst","Detail":"Substitution 2","Comments":null},{"Time":{"Elapsed":67,"Extra":null},"Team":{"Id":91,"Name":"Monaco","Logo":"https://media.api-sports.io/football/teams/91.png"},"Player":{"Id":21998,"Name":"Axel Disasi"},"Assist":{"Id":null,"Name":null},"Type":"Card","Detail":"Yellow Card","Comments":"Foul"},{"Time":{"Elapsed":69,"Extra":null},"Team":{"Id":91,"Name":"Monaco","Logo":"https://media.api-sports.io/football/teams/91.png"},"Player":{"Id":10316,"Name":"Caio Henrique"},"Assist":{"Id":105,"Name":"F. Ballo"},"Type":"subst","Detail":"Substitution 4","Comments":null},{"Time":{"Elapsed":76,"Extra":null},"Team":{"Id":81,"Name":"Marseille","Logo":"https://media.api-sports.io/football/teams/81.png"},"Player":{"Id":1904,"Name":"Boubacar Kamara"},"Assist":{"Id":null,"Name":null},"Type":"Card","Detail":"Yellow Card","Comments":"Foul"},{"Time":{"Elapsed":76,"Extra":null},"Team":{"Id":91,"Name":"Monaco","Logo":"https://media.api-sports.io/football/teams/91.png"},"Player":{"Id":1271,"Name":"A. Tchouam\u00E9ni"},"Assist":{"Id":162887,"Name":"E. Millot"},"Type":"subst","Detail":"Substitution 5","Comments":null},{"Time":{"Elapsed":77,"Extra":null},"Team":{"Id":81,"Name":"Marseille","Logo":"https://media.api-sports.io/football/teams/81.png"},"Player":{"Id":1922,"Name":"Florian Thauvin"},"Assist":{"Id":null,"Name":null},"Type":"Card","Detail":"Yellow Card","Comments":"Foul"},{"Time":{"Elapsed":79,"Extra":null},"Team":{"Id":91,"Name":"Monaco","Logo":"https://media.api-sports.io/football/teams/91.png"},"Player":{"Id":2059,"Name":"W. Ben Yedder"},"Assist":{"Id":null,"Name":null},"Type":"Goal","Detail":"Penalty","Comments":null},{"Time":{"Elapsed":87,"Extra":null},"Team":{"Id":81,"Name":"Marseille","Logo":"https://media.api-sports.io/football/teams/81.png"},"Player":{"Id":1922,"Name":"F. Thauvin"},"Assist":{"Id":10077,"Name":"Luis Henrique"},"Type":"subst","Detail":"Substitution 3","Comments":null},{"Time":{"Elapsed":87,"Extra":null},"Team":{"Id":81,"Name":"Marseille","Logo":"https://media.api-sports.io/football/teams/81.png"},"Player":{"Id":2478,"Name":"D. Benedetto"},"Assist":{"Id":6,"Name":"L. Balerdi"},"Type":"subst","Detail":"Substitution 4","Comments":null},{"Time":{"Elapsed":90,"Extra":null},"Team":{"Id":81,"Name":"Marseille","Logo":"https://media.api-sports.io/football/teams/81.png"},"Player":{"Id":1918,"Name":"Val\u00E8re Germain"},"Assist":{"Id":null,"Name":null},"Type":"Card","Detail":"Yellow Card","Comments":"Foul"}],"Lineups":[{"Team":{"Id":81,"Name":"Marseille","Logo":"https://media.api-sports.io/football/teams/81.png","Colors":null},"Formation":"4-3-1-2","StartXI":[{"Player":{"Id":1897,"Name":"S. Mandanda","Number":30,"Pos":"G","Grid":"1:1"}},{"Player":{"Id":440,"Name":"Y. Nagatomo","Number":25,"Pos":"D","Grid":"2:4"}},{"Player":{"Id":1907,"Name":"H. Sakai","Number":2,"Pos":"D","Grid":"2:3"}},{"Player":{"Id":1689,"Name":"\u00C1lvaro Gonz\u00E1lez","Number":3,"Pos":"D","Grid":"2:2"}},{"Player":{"Id":1902,"Name":"D. \u0106aleta-Car","Number":15,"Pos":"D","Grid":"2:1"}},{"Player":{"Id":1904,"Name":"B. Kamara","Number":4,"Pos":"M","Grid":"3:3"}},{"Player":{"Id":1914,"Name":"M. Sanson","Number":8,"Pos":"M","Grid":"3:2"}},{"Player":{"Id":21102,"Name":"V. Rongier","Number":21,"Pos":"M","Grid":"3:1"}},{"Player":{"Id":25634,"Name":"M. Cuisance","Number":17,"Pos":"M","Grid":"4:1"}},{"Player":{"Id":2478,"Name":"D. Benedetto","Number":9,"Pos":"F","Grid":"5:2"}},{"Player":{"Id":1922,"Name":"F. Thauvin","Number":26,"Pos":"F","Grid":"5:1"}}],"Substitutes":[{"Player":{"Id":20696,"Name":"P. Gueye","Number":22,"Pos":"M","Grid":null}},{"Player":{"Id":1918,"Name":"V. Germain","Number":28,"Pos":"F","Grid":null}},{"Player":{"Id":6,"Name":"L. Balerdi","Number":5,"Pos":"D","Grid":null}},{"Player":{"Id":10077,"Name":"Luis Henrique","Number":11,"Pos":"F","Grid":null}},{"Player":{"Id":2955,"Name":"S. Khaoui","Number":24,"Pos":"M","Grid":null}},{"Player":{"Id":129687,"Name":"M. Ak\u00E9","Number":23,"Pos":"M","Grid":null}},{"Player":{"Id":67953,"Name":"L. Perrin","Number":32,"Pos":"D","Grid":null}},{"Player":{"Id":1898,"Name":"Y. Pel\u00E9","Number":16,"Pos":"G","Grid":null}},{"Player":{"Id":1916,"Name":"K. Strootman","Number":6,"Pos":"M","Grid":null}}],"Coach":{"Id":24,"Name":"Andr\u00E9 Villas-Boas","Photo":"https://media.api-sports.io/football/coachs/24.png"}},{"Team":{"Id":91,"Name":"Monaco","Logo":"https://media.api-sports.io/football/teams/91.png","Colors":null},"Formation":"4-4-2","StartXI":[{"Player":{"Id":51146,"Name":"V. Mannone","Number":30,"Pos":"G","Grid":"1:1"}},{"Player":{"Id":21568,"Name":"R. Aguilar","Number":26,"Pos":"D","Grid":"2:4"}},{"Player":{"Id":21998,"Name":"A. Disasi","Number":20,"Pos":"D","Grid":"2:3"}},{"Player":{"Id":95,"Name":"B. Badiashile","Number":32,"Pos":"D","Grid":"2:2"}},{"Player":{"Id":10316,"Name":"Caio Henrique","Number":12,"Pos":"D","Grid":"2:1"}},{"Player":{"Id":1271,"Name":"A. Tchouam\u00E9ni","Number":8,"Pos":"M","Grid":"3:4"}},{"Player":{"Id":22254,"Name":"Y. Fofana","Number":22,"Pos":"M","Grid":"3:3"}},{"Player":{"Id":989,"Name":"K. Volland","Number":31,"Pos":"F","Grid":"3:2"}},{"Player":{"Id":2059,"Name":"W. Ben Yedder","Number":9,"Pos":"F","Grid":"3:1"}},{"Player":{"Id":118,"Name":"Gelson Martins","Number":11,"Pos":"M","Grid":"4:2"}},{"Player":{"Id":107,"Name":"S. Diop","Number":37,"Pos":"M","Grid":"4:1"}}],"Substitutes":[{"Player":{"Id":2553,"Name":"G. Marip\u00E1n","Number":3,"Pos":"D","Grid":null}},{"Player":{"Id":123,"Name":"P. Pellegri","Number":19,"Pos":"F","Grid":null}},{"Player":{"Id":121,"Name":"S. Joveti\u0107","Number":10,"Pos":"F","Grid":null}},{"Player":{"Id":105,"Name":"F. Ballo","Number":2,"Pos":"D","Grid":null}},{"Player":{"Id":162887,"Name":"E. Millot","Number":38,"Pos":"F","Grid":null}},{"Player":{"Id":120,"Name":"W. Geubbels","Number":13,"Pos":"F","Grid":null}},{"Player":{"Id":163039,"Name":"C. Matsima","Number":34,"Pos":"D","Grid":null}},{"Player":{"Id":162991,"Name":"E. Matazo","Number":36,"Pos":"M","Grid":null}},{"Player":{"Id":40384,"Name":"R. Majecki","Number":1,"Pos":"G","Grid":null}}],"Coach":{"Id":1528,"Name":"N. Kova\u010D","Photo":"https://media.api-sports.io/football/coachs/1528.png"}}],"Statistics":[{"Team":{"Id":81,"Name":"Marseille","Logo":"https://media.api-sports.io/football/teams/81.png"},"Statistics":[{"Type":"Shots on Goal","Value":2},{"Type":"Shots off Goal","Value":2},{"Type":"Total Shots","Value":5},{"Type":"Blocked Shots","Value":1},{"Type":"Shots insidebox","Value":4},{"Type":"Shots outsidebox","Value":1},{"Type":"Fouls","Value":22},{"Type":"Corner Kicks","Value":1},{"Type":"Offsides","Value":1},{"Type":"Ball Possession","Value":"39%"},{"Type":"Yellow Cards","Value":3},{"Type":"Red Cards","Value":null},{"Type":"Goalkeeper Saves","Value":3},{"Type":"Total passes","Value":355},{"Type":"Passes accurate","Value":243},{"Type":"Passes %","Value":"68%"}]},{"Team":{"Id":91,"Name":"Monaco","Logo":"https://media.api-sports.io/football/teams/91.png"},"Statistics":[{"Type":"Shots on Goal","Value":4},{"Type":"Shots off Goal","Value":4},{"Type":"Total Shots","Value":9},{"Type":"Blocked Shots","Value":1},{"Type":"Shots insidebox","Value":8},{"Type":"Shots outsidebox","Value":1},{"Type":"Fouls","Value":10},{"Type":"Corner Kicks","Value":3},{"Type":"Offsides","Value":4},{"Type":"Ball Possession","Value":"61%"},{"Type":"Yellow Cards","Value":2},{"Type":"Red Cards","Value":null},{"Type":"Goalkeeper Saves","Value":null},{"Type":"Total passes","Value":551},{"Type":"Passes accurate","Value":433},{"Type":"Passes %","Value":"79%"}]}],"Players":[{"Team":{"Id":81,"Name":"Marseille","Logo":"https://media.api-sports.io/football/teams/81.png","Update":"2021-05-17T19:12:13+02:00"},"Players":[{"Player":{"Id":1897,"Name":"Steve Mandanda","Photo":"https://media.api-sports.io/football/players/1897.png"},"Statistics":[{"Games":{"Minutes":90,"Number":30,"Position":"G","Rating":"6.9","Captain":true,"Substitute":false},"Offsides":null,"Shots":{"Total":null,"On":null},"Goals":{"Total":null,"Conceded":1,"Assists":null,"Saves":3},"Passes":{"Total":32,"Key":null,"Accuracy":"8"},"Tackles":{"Total":null,"Blocks":null,"Interceptions":null},"Duels":{"Total":1,"Won":1},"Dribbles":{"Attempts":null,"Success":null,"Past":null},"Fouls":{"Drawn":null,"Committed":null},"Cards":{"Yellow":0,"Red":0},"Penalty":{"Won":null,"Commited":null,"Scored":0,"Missed":0,"Saved":0}}]},{"Player":{"Id":1907,"Name":"Hiroki Sakai","Photo":"https://media.api-sports.io/football/players/1907.png"},"Statistics":[{"Games":{"Minutes":90,"Number":2,"Position":"D","Rating":"7.2","Captain":false,"Substitute":false},"Offsides":null,"Shots":{"Total":null,"On":null},"Goals":{"Total":null,"Conceded":0,"Assists":null,"Saves":null},"Passes":{"Total":34,"Key":null,"Accuracy":"22"},"Tackles":{"Total":5,"Blocks":null,"Interceptions":3},"Duels":{"Total":12,"Won":8},"Dribbles":{"Attempts":1,"Success":null,"Past":null},"Fouls":{"Drawn":1,"Committed":1},"Cards":{"Yellow":0,"Red":0},"Penalty":{"Won":null,"Commited":null,"Scored":0,"Missed":0,"Saved":null}}]},{"Player":{"Id":1689,"Name":"\u00C1lvaro Gonz\u00E1lez","Photo":"https://media.api-sports.io/football/players/1689.png"},"Statistics":[{"Games":{"Minutes":90,"Number":3,"Position":"D","Rating":"6.9","Captain":false,"Substitute":false},"Offsides":null,"Shots":{"Total":1,"On":null},"Goals":{"Total":null,"Conceded":0,"Assists":null,"Saves":null},"Passes":{"Total":28,"Key":null,"Accuracy":"24"},"Tackles":{"Total":2,"Blocks":null,"Interceptions":2},"Duels":{"Total":3,"Won":3},"Dribbles":{"Attempts":null,"Success":null,"Past":null},"Fouls":{"Drawn":1,"Committed":null},"Cards":{"Yellow":0,"Red":0},"Penalty":{"Won":null,"Commited":null,"Scored":0,"Missed":0,"Saved":null}}]},{"Player":{"Id":1902,"Name":"Duje \u0106aleta-Car","Photo":"https://media.api-sports.io/football/players/1902.png"},"Statistics":[{"Games":{"Minutes":90,"Number":15,"Position":"D","Rating":"7","Captain":false,"Substitute":false},"Offsides":null,"Shots":{"Total":null,"On":null},"Goals":{"Total":null,"Conceded":0,"Assists":null,"Saves":null},"Passes":{"Total":41,"Key":null,"Accuracy":"30"},"Tackles":{"Total":null,"Blocks":1,"Interceptions":2},"Duels":{"Total":7,"Won":6},"Dribbles":{"Attempts":null,"Success":null,"Past":null},"Fouls":{"Drawn":null,"Committed":null},"Cards":{"Yellow":0,"Red":0},"Penalty":{"Won":null,"Commited":null,"Scored":0,"Missed":0,"Saved":null}}]},{"Player":{"Id":440,"Name":"Yuto Nagatomo","Photo":"https://media.api-sports.io/football/players/440.png"},"Statistics":[{"Games":{"Minutes":90,"Number":25,"Position":"D","Rating":"6","Captain":false,"Substitute":false},"Offsides":null,"Shots":{"Total":null,"On":null},"Goals":{"Total":null,"Conceded":0,"Assists":null,"Saves":null},"Passes":{"Total":39,"Key":null,"Accuracy":"25"},"Tackles":{"Total":null,"Blocks":null,"Interceptions":null},"Duels":{"Total":8,"Won":2},"Dribbles":{"Attempts":null,"Success":null,"Past":3},"Fouls":{"Drawn":null,"Committed":2},"Cards":{"Yellow":0,"Red":0},"Penalty":{"Won":null,"Commited":null,"Scored":0,"Missed":0,"Saved":null}}]},{"Player":{"Id":21102,"Name":"Valentin Rongier","Photo":"https://media.api-sports.io/football/players/21102.png"},"Statistics":[{"Games":{"Minutes":90,"Number":21,"Position":"M","Rating":"7.2","Captain":false,"Substitute":false},"Offsides":null,"Shots":{"Total":null,"On":null},"Goals":{"Total":null,"Conceded":0,"Assists":null,"Saves":null},"Passes":{"Total":43,"Key":1,"Accuracy":"36"},"Tackles":{"Total":5,"Blocks":null,"Interceptions":1},"Duels":{"Total":14,"Won":7},"Dribbles":{"Attempts":2,"Success":1,"Past":null},"Fouls":{"Drawn":null,"Committed":3},"Cards":{"Yellow":0,"Red":0},"Penalty":{"Won":null,"Commited":null,"Scored":0,"Missed":0,"Saved":null}}]},{"Player":{"Id":1904,"Name":"Boubacar Kamara","Photo":"https://media.api-sports.io/football/players/1904.png"},"Statistics":[{"Games":{"Minutes":90,"Number":4,"Position":"M","Rating":"6.3","Captain":false,"Substitute":false},"Offsides":null,"Shots":{"Total":null,"On":null},"Goals":{"Total":null,"Conceded":0,"Assists":null,"Saves":null},"Passes":{"Total":36,"Key":null,"Accuracy":"24"},"Tackles":{"Total":2,"Blocks":null,"Interceptions":2},"Duels":{"Total":18,"Won":8},"Dribbles":{"Attempts":2,"Success":2,"Past":2},"Fouls":{"Drawn":1,"Committed":3},"Cards":{"Yellow":1,"Red":0},"Penalty":{"Won":null,"Commited":null,"Scored":0,"Missed":0,"Saved":null}}]},{"Player":{"Id":1914,"Name":"Morgan Sanson","Photo":"https://media.api-sports.io/football/players/1914.png"},"Statistics":[{"Games":{"Minutes":24,"Number":8,"Position":"M","Rating":"6.3","Captain":false,"Substitute":false},"Offsides":null,"Shots":{"Total":null,"On":null},"Goals":{"Total":null,"Conceded":0,"Assists":null,"Saves":null},"Passes":{"Total":7,"Key":null,"Accuracy":"3"},"Tackles":{"Total":null,"Blocks":null,"Interceptions":null},"Duels":{"Total":3,"Won":null},"Dribbles":{"Attempts":1,"Success":null,"Past":null},"Fouls":{"Drawn":null,"Committed":2},"Cards":{"Yellow":0,"Red":0},"Penalty":{"Won":null,"Commited":null,"Scored":0,"Missed":0,"Saved":null}}]},{"Player":{"Id":25634,"Name":"Micha\u00EBl Cuisance","Photo":"https://media.api-sports.io/football/players/25634.png"},"Statistics":[{"Games":{"Minutes":65,"Number":17,"Position":"M","Rating":"6.2","Captain":false,"Substitute":false},"Offsides":null,"Shots":{"Total":null,"On":null},"Goals":{"Total":null,"Conceded":0,"Assists":null,"Saves":null},"Passes":{"Total":19,"Key":null,"Accuracy":"14"},"Tackles":{"Total":3,"Blocks":null,"Interceptions":null},"Duels":{"Total":15,"Won":4},"Dribbles":{"Attempts":3,"Success":1,"Past":2},"Fouls":{"Drawn":null,"Committed":1},"Cards":{"Yellow":0,"Red":0},"Penalty":{"Won":null,"Commited":null,"Scored":0,"Missed":0,"Saved":null}}]},{"Player":{"Id":2478,"Name":"Dar\u00EDo Benedetto","Photo":"https://media.api-sports.io/football/players/2478.png"},"Statistics":[{"Games":{"Minutes":87,"Number":9,"Position":"F","Rating":"8.3","Captain":false,"Substitute":false},"Offsides":null,"Shots":{"Total":1,"On":1},"Goals":{"Total":1,"Conceded":0,"Assists":1,"Saves":null},"Passes":{"Total":17,"Key":2,"Accuracy":"15"},"Tackles":{"Total":1,"Blocks":null,"Interceptions":null},"Duels":{"Total":11,"Won":5},"Dribbles":{"Attempts":null,"Success":null,"Past":null},"Fouls":{"Drawn":4,"Committed":2},"Cards":{"Yellow":0,"Red":0},"Penalty":{"Won":null,"Commited":null,"Scored":0,"Missed":0,"Saved":null}}]},{"Player":{"Id":1922,"Name":"Florian Thauvin","Photo":"https://media.api-sports.io/football/players/1922.png"},"Statistics":[{"Games":{"Minutes":87,"Number":26,"Position":"F","Rating":"7.9","Captain":false,"Substitute":false},"Offsides":null,"Shots":{"Total":2,"On":1},"Goals":{"Total":1,"Conceded":0,"Assists":1,"Saves":null},"Passes":{"Total":26,"Key":2,"Accuracy":"21"},"Tackles":{"Total":1,"Blocks":null,"Interceptions":null},"Duels":{"Total":6,"Won":1},"Dribbles":{"Attempts":1,"Success":null,"Past":1},"Fouls":{"Drawn":null,"Committed":2},"Cards":{"Yellow":1,"Red":0},"Penalty":{"Won":null,"Commited":1,"Scored":0,"Missed":0,"Saved":null}}]},{"Player":{"Id":1898,"Name":"Yohann Pel\u00E9","Photo":"https://media.api-sports.io/football/players/1898.png"},"Statistics":[{"Games":{"Minutes":null,"Number":16,"Position":"G","Rating":null,"Captain":false,"Substitute":true},"Offsides":null,"Shots":{"Total":null,"On":null},"Goals":{"Total":null,"Conceded":0,"Assists":null,"Saves":null},"Passes":{"Total":null,"Key":null,"Accuracy":null},"Tackles":{"Total":null,"Blocks":null,"Interceptions":null},"Duels":{"Total":null,"Won":null},"Dribbles":{"Attempts":null,"Success":null,"Past":null},"Fouls":{"Drawn":null,"Committed":null},"Cards":{"Yellow":0,"Red":0},"Penalty":{"Won":null,"Commited":null,"Scored":0,"Missed":0,"Saved":null}}]},{"Player":{"Id":6,"Name":"Leonardo Balerdi","Photo":"https://media.api-sports.io/football/players/6.png"},"Statistics":[{"Games":{"Minutes":9,"Number":5,"Position":"D","Rating":"6.7","Captain":false,"Substitute":true},"Offsides":null,"Shots":{"Total":null,"On":null},"Goals":{"Total":null,"Conceded":0,"Assists":null,"Saves":null},"Passes":{"Total":1,"Key":null,"Accuracy":"1"},"Tackles":{"Total":null,"Blocks":null,"Interceptions":null},"Duels":{"Total":null,"Won":null},"Dribbles":{"Attempts":null,"Success":null,"Past":null},"Fouls":{"Drawn":null,"Committed":null},"Cards":{"Yellow":0,"Red":0},"Penalty":{"Won":null,"Commited":null,"Scored":0,"Missed":0,"Saved":null}}]},{"Player":{"Id":67953,"Name":"Lucas Perrin","Photo":"https://media.api-sports.io/football/players/67953.png"},"Statistics":[{"Games":{"Minutes":null,"Number":32,"Position":"D","Rating":null,"Captain":false,"Substitute":true},"Offsides":null,"Shots":{"Total":null,"On":null},"Goals":{"Total":null,"Conceded":0,"Assists":null,"Saves":null},"Passes":{"Total":null,"Key":null,"Accuracy":null},"Tackles":{"Total":null,"Blocks":null,"Interceptions":null},"Duels":{"Total":null,"Won":null},"Dribbles":{"Attempts":null,"Success":null,"Past":null},"Fouls":{"Drawn":null,"Committed":null},"Cards":{"Yellow":0,"Red":0},"Penalty":{"Won":null,"Commited":null,"Scored":0,"Missed":0,"Saved":null}}]},{"Player":{"Id":2955,"Name":"Sa\u00EEf-Eddine Khaoui","Photo":"https://media.api-sports.io/football/players/2955.png"},"Statistics":[{"Games":{"Minutes":null,"Number":24,"Position":"M","Rating":null,"Captain":false,"Substitute":true},"Offsides":null,"Shots":{"Total":null,"On":null},"Goals":{"Total":null,"Conceded":0,"Assists":null,"Saves":null},"Passes":{"Total":null,"Key":null,"Accuracy":null},"Tackles":{"Total":null,"Blocks":null,"Interceptions":null},"Duels":{"Total":null,"Won":null},"Dribbles":{"Attempts":null,"Success":null,"Past":null},"Fouls":{"Drawn":null,"Committed":null},"Cards":{"Yellow":0,"Red":0},"Penalty":{"Won":null,"Commited":null,"Scored":0,"Missed":0,"Saved":null}}]},{"Player":{"Id":1916,"Name":"Kevin Strootman","Photo":"https://media.api-sports.io/football/players/1916.png"},"Statistics":[{"Games":{"Minutes":null,"Number":6,"Position":"M","Rating":null,"Captain":false,"Substitute":true},"Offsides":null,"Shots":{"Total":null,"On":null},"Goals":{"Total":null,"Conceded":0,"Assists":null,"Saves":null},"Passes":{"Total":null,"Key":null,"Accuracy":null},"Tackles":{"Total":null,"Blocks":null,"Interceptions":null},"Duels":{"Total":null,"Won":null},"Dribbles":{"Attempts":null,"Success":null,"Past":null},"Fouls":{"Drawn":null,"Committed":null},"Cards":{"Yellow":0,"Red":0},"Penalty":{"Won":null,"Commited":null,"Scored":0,"Missed":0,"Saved":null}}]},{"Player":{"Id":20696,"Name":"Pape Gueye","Photo":"https://media.api-sports.io/football/players/20696.png"},"Statistics":[{"Games":{"Minutes":66,"Number":22,"Position":"M","Rating":"6.9","Captain":false,"Substitute":true},"Offsides":null,"Shots":{"Total":null,"On":null},"Goals":{"Total":null,"Conceded":0,"Assists":null,"Saves":null},"Passes":{"Total":17,"Key":null,"Accuracy":"11"},"Tackles":{"Total":4,"Blocks":null,"Interceptions":null},"Duels":{"Total":19,"Won":10},"Dribbles":{"Attempts":1,"Success":1,"Past":1},"Fouls":{"Drawn":1,"Committed":4},"Cards":{"Yellow":0,"Red":0},"Penalty":{"Won":null,"Commited":null,"Scored":0,"Missed":0,"Saved":null}}]},{"Player":{"Id":10077,"Name":"Luis Henrique","Photo":"https://media.api-sports.io/football/players/10077.png"},"Statistics":[{"Games":{"Minutes":9,"Number":11,"Position":"F","Rating":"6.5","Captain":false,"Substitute":true},"Offsides":null,"Shots":{"Total":null,"On":null},"Goals":{"Total":null,"Conceded":0,"Assists":null,"Saves":null},"Passes":{"Total":3,"Key":null,"Accuracy":"2"},"Tackles":{"Total":null,"Blocks":null,"Interceptions":null},"Duels":{"Total":3,"Won":1},"Dribbles":{"Attempts":3,"Success":1,"Past":null},"Fouls":{"Drawn":null,"Committed":null},"Cards":{"Yellow":0,"Red":0},"Penalty":{"Won":null,"Commited":null,"Scored":0,"Missed":0,"Saved":null}}]},{"Player":{"Id":1918,"Name":"Val\u00E8re Germain","Photo":"https://media.api-sports.io/football/players/1918.png"},"Statistics":[{"Games":{"Minutes":25,"Number":28,"Position":"F","Rating":"6.3","Captain":false,"Substitute":true},"Offsides":null,"Shots":{"Total":null,"On":null},"Goals":{"Total":null,"Conceded":0,"Assists":null,"Saves":null},"Passes":{"Total":12,"Key":null,"Accuracy":"7"},"Tackles":{"Total":null,"Blocks":null,"Interceptions":2},"Duels":{"Total":10,"Won":4},"Dribbles":{"Attempts":1,"Success":null,"Past":1},"Fouls":{"Drawn":1,"Committed":2},"Cards":{"Yellow":1,"Red":0},"Penalty":{"Won":null,"Commited":null,"Scored":0,"Missed":0,"Saved":null}}]},{"Player":{"Id":129687,"Name":"Marley Ak\u00E9","Photo":"https://media.api-sports.io/football/players/129687.png"},"Statistics":[{"Games":{"Minutes":null,"Number":23,"Position":"M","Rating":null,"Captain":false,"Substitute":true},"Offsides":null,"Shots":{"Total":null,"On":null},"Goals":{"Total":null,"Conceded":0,"Assists":null,"Saves":null},"Passes":{"Total":null,"Key":null,"Accuracy":null},"Tackles":{"Total":null,"Blocks":null,"Interceptions":null},"Duels":{"Total":null,"Won":null},"Dribbles":{"Attempts":null,"Success":null,"Past":null},"Fouls":{"Drawn":null,"Committed":null},"Cards":{"Yellow":0,"Red":0},"Penalty":{"Won":null,"Commited":null,"Scored":0,"Missed":0,"Saved":null}}]}]},{"Team":{"Id":91,"Name":"Monaco","Logo":"https://media.api-sports.io/football/teams/91.png","Update":"2021-05-17T19:12:13+02:00"},"Players":[{"Player":{"Id":51146,"Name":"Vito Mannone","Photo":"https://media.api-sports.io/football/players/51146.png"},"Statistics":[{"Games":{"Minutes":90,"Number":30,"Position":"G","Rating":"6","Captain":false,"Substitute":false},"Offsides":null,"Shots":{"Total":null,"On":null},"Goals":{"Total":null,"Conceded":2,"Assists":null,"Saves":null},"Passes":{"Total":25,"Key":null,"Accuracy":"20"},"Tackles":{"Total":null,"Blocks":null,"Interceptions":null},"Duels":{"Total":null,"Won":null},"Dribbles":{"Attempts":null,"Success":null,"Past":null},"Fouls":{"Drawn":null,"Committed":null},"Cards":{"Yellow":0,"Red":0},"Penalty":{"Won":null,"Commited":null,"Scored":0,"Missed":0,"Saved":0}}]},{"Player":{"Id":21568,"Name":"Ruben Aguilar","Photo":"https://media.api-sports.io/football/players/21568.png"},"Statistics":[{"Games":{"Minutes":90,"Number":26,"Position":"D","Rating":"8","Captain":false,"Substitute":false},"Offsides":null,"Shots":{"Total":null,"On":null},"Goals":{"Total":null,"Conceded":0,"Assists":null,"Saves":null},"Passes":{"Total":72,"Key":4,"Accuracy":"55"},"Tackles":{"Total":3,"Blocks":null,"Interceptions":4},"Duels":{"Total":15,"Won":9},"Dribbles":{"Attempts":2,"Success":1,"Past":null},"Fouls":{"Drawn":3,"Committed":2},"Cards":{"Yellow":0,"Red":0},"Penalty":{"Won":null,"Commited":null,"Scored":0,"Missed":0,"Saved":null}}]},{"Player":{"Id":21998,"Name":"Axel Disasi","Photo":"https://media.api-sports.io/football/players/21998.png"},"Statistics":[{"Games":{"Minutes":90,"Number":20,"Position":"D","Rating":"6.7","Captain":false,"Substitute":false},"Offsides":null,"Shots":{"Total":1,"On":null},"Goals":{"Total":null,"Conceded":0,"Assists":null,"Saves":null},"Passes":{"Total":62,"Key":null,"Accuracy":"49"},"Tackles":{"Total":null,"Blocks":null,"Interceptions":null},"Duels":{"Total":13,"Won":9},"Dribbles":{"Attempts":null,"Success":null,"Past":null},"Fouls":{"Drawn":2,"Committed":3},"Cards":{"Yellow":1,"Red":0},"Penalty":{"Won":null,"Commited":null,"Scored":0,"Missed":0,"Saved":null}}]},{"Player":{"Id":95,"Name":"Beno\u00EEt Badiashile","Photo":"https://media.api-sports.io/football/players/95.png"},"Statistics":[{"Games":{"Minutes":45,"Number":32,"Position":"D","Rating":"6.5","Captain":false,"Substitute":false},"Offsides":null,"Shots":{"Total":1,"On":1},"Goals":{"Total":null,"Conceded":0,"Assists":null,"Saves":null},"Passes":{"Total":24,"Key":null,"Accuracy":"22"},"Tackles":{"Total":1,"Blocks":null,"Interceptions":null},"Duels":{"Total":3,"Won":2},"Dribbles":{"Attempts":null,"Success":null,"Past":1},"Fouls":{"Drawn":null,"Committed":null},"Cards":{"Yellow":0,"Red":0},"Penalty":{"Won":null,"Commited":null,"Scored":0,"Missed":0,"Saved":null}}]},{"Player":{"Id":10316,"Name":"Caio Henrique","Photo":"https://media.api-sports.io/football/players/10316.png"},"Statistics":[{"Games":{"Minutes":69,"Number":12,"Position":"D","Rating":"6.2","Captain":false,"Substitute":false},"Offsides":null,"Shots":{"Total":null,"On":null},"Goals":{"Total":null,"Conceded":0,"Assists":null,"Saves":null},"Passes":{"Total":39,"Key":1,"Accuracy":"30"},"Tackles":{"Total":null,"Blocks":null,"Interceptions":null},"Duels":{"Total":6,"Won":3},"Dribbles":{"Attempts":1,"Success":null,"Past":null},"Fouls":{"Drawn":1,"Committed":null},"Cards":{"Yellow":0,"Red":0},"Penalty":{"Won":null,"Commited":null,"Scored":0,"Missed":0,"Saved":null}}]},{"Player":{"Id":107,"Name":"Sofiane Diop","Photo":"https://media.api-sports.io/football/players/107.png"},"Statistics":[{"Games":{"Minutes":90,"Number":37,"Position":"M","Rating":"7.7","Captain":false,"Substitute":false},"Offsides":null,"Shots":{"Total":null,"On":null},"Goals":{"Total":null,"Conceded":0,"Assists":null,"Saves":null},"Passes":{"Total":59,"Key":null,"Accuracy":"50"},"Tackles":{"Total":1,"Blocks":null,"Interceptions":4},"Duels":{"Total":18,"Won":14},"Dribbles":{"Attempts":6,"Success":5,"Past":null},"Fouls":{"Drawn":8,"Committed":null},"Cards":{"Yellow":0,"Red":0},"Penalty":{"Won":null,"Commited":null,"Scored":0,"Missed":0,"Saved":null}}]},{"Player":{"Id":1271,"Name":"Aurelien Tchouameni","Photo":"https://media.api-sports.io/football/players/1271.png"},"Statistics":[{"Games":{"Minutes":76,"Number":8,"Position":"M","Rating":"6.9","Captain":false,"Substitute":false},"Offsides":null,"Shots":{"Total":1,"On":1},"Goals":{"Total":null,"Conceded":0,"Assists":null,"Saves":null},"Passes":{"Total":54,"Key":null,"Accuracy":"42"},"Tackles":{"Total":2,"Blocks":null,"Interceptions":null},"Duels":{"Total":9,"Won":6},"Dribbles":{"Attempts":1,"Success":null,"Past":1},"Fouls":{"Drawn":2,"Committed":null},"Cards":{"Yellow":0,"Red":0},"Penalty":{"Won":null,"Commited":null,"Scored":0,"Missed":0,"Saved":null}}]},{"Player":{"Id":22254,"Name":"Youssouf Fofana","Photo":"https://media.api-sports.io/football/players/22254.png"},"Statistics":[{"Games":{"Minutes":90,"Number":22,"Position":"M","Rating":"6.5","Captain":false,"Substitute":false},"Offsides":null,"Shots":{"Total":null,"On":null},"Goals":{"Total":null,"Conceded":0,"Assists":null,"Saves":null},"Passes":{"Total":64,"Key":null,"Accuracy":"48"},"Tackles":{"Total":4,"Blocks":null,"Interceptions":1},"Duels":{"Total":10,"Won":4},"Dribbles":{"Attempts":null,"Success":null,"Past":2},"Fouls":{"Drawn":null,"Committed":1},"Cards":{"Yellow":1,"Red":0},"Penalty":{"Won":null,"Commited":null,"Scored":0,"Missed":0,"Saved":null}}]},{"Player":{"Id":118,"Name":"Gelson Martins","Photo":"https://media.api-sports.io/football/players/118.png"},"Statistics":[{"Games":{"Minutes":59,"Number":11,"Position":"M","Rating":"6.3","Captain":false,"Substitute":false},"Offsides":null,"Shots":{"Total":null,"On":null},"Goals":{"Total":null,"Conceded":0,"Assists":null,"Saves":null},"Passes":{"Total":16,"Key":null,"Accuracy":"9"},"Tackles":{"Total":1,"Blocks":null,"Interceptions":null},"Duels":{"Total":9,"Won":3},"Dribbles":{"Attempts":3,"Success":1,"Past":null},"Fouls":{"Drawn":1,"Committed":2},"Cards":{"Yellow":0,"Red":0},"Penalty":{"Won":null,"Commited":null,"Scored":0,"Missed":0,"Saved":null}}]},{"Player":{"Id":989,"Name":"Kevin Volland","Photo":"https://media.api-sports.io/football/players/989.png"},"Statistics":[{"Games":{"Minutes":58,"Number":31,"Position":"F","Rating":"6.3","Captain":false,"Substitute":false},"Offsides":null,"Shots":{"Total":null,"On":null},"Goals":{"Total":null,"Conceded":0,"Assists":null,"Saves":null},"Passes":{"Total":19,"Key":null,"Accuracy":"13"},"Tackles":{"Total":1,"Blocks":null,"Interceptions":null},"Duels":{"Total":11,"Won":4},"Dribbles":{"Attempts":null,"Success":null,"Past":1},"Fouls":{"Drawn":1,"Committed":1},"Cards":{"Yellow":0,"Red":0},"Penalty":{"Won":null,"Commited":null,"Scored":0,"Missed":0,"Saved":null}}]},{"Player":{"Id":2059,"Name":"Wissam Ben Yedder","Photo":"https://media.api-sports.io/football/players/2059.png"},"Statistics":[{"Games":{"Minutes":90,"Number":9,"Position":"F","Rating":"7.2","Captain":true,"Substitute":false},"Offsides":null,"Shots":{"Total":2,"On":1},"Goals":{"Total":1,"Conceded":0,"Assists":null,"Saves":null},"Passes":{"Total":27,"Key":2,"Accuracy":"21"},"Tackles":{"Total":null,"Blocks":null,"Interceptions":null},"Duels":{"Total":14,"Won":5},"Dribbles":{"Attempts":1,"Success":1,"Past":null},"Fouls":{"Drawn":1,"Committed":null},"Cards":{"Yellow":0,"Red":0},"Penalty":{"Won":1,"Commited":null,"Scored":1,"Missed":0,"Saved":null}}]},{"Player":{"Id":40384,"Name":"Rados\u0142aw Majecki","Photo":"https://media.api-sports.io/football/players/40384.png"},"Statistics":[{"Games":{"Minutes":null,"Number":1,"Position":"G","Rating":null,"Captain":false,"Substitute":true},"Offsides":null,"Shots":{"Total":null,"On":null},"Goals":{"Total":null,"Conceded":0,"Assists":null,"Saves":null},"Passes":{"Total":null,"Key":null,"Accuracy":null},"Tackles":{"Total":null,"Blocks":null,"Interceptions":null},"Duels":{"Total":null,"Won":null},"Dribbles":{"Attempts":null,"Success":null,"Past":null},"Fouls":{"Drawn":null,"Committed":null},"Cards":{"Yellow":0,"Red":0},"Penalty":{"Won":null,"Commited":null,"Scored":0,"Missed":0,"Saved":null}}]},{"Player":{"Id":2553,"Name":"Guillermo Marip\u00E1n","Photo":"https://media.api-sports.io/football/players/2553.png"},"Statistics":[{"Games":{"Minutes":45,"Number":3,"Position":"D","Rating":"6.6","Captain":false,"Substitute":true},"Offsides":null,"Shots":{"Total":null,"On":null},"Goals":{"Total":null,"Conceded":0,"Assists":null,"Saves":null},"Passes":{"Total":49,"Key":null,"Accuracy":"43"},"Tackles":{"Total":1,"Blocks":null,"Interceptions":null},"Duels":{"Total":3,"Won":2},"Dribbles":{"Attempts":null,"Success":null,"Past":1},"Fouls":{"Drawn":null,"Committed":null},"Cards":{"Yellow":0,"Red":0},"Penalty":{"Won":null,"Commited":null,"Scored":0,"Missed":0,"Saved":null}}]},{"Player":{"Id":105,"Name":"Fod\u00E9 Ballo-Tour\u00E9","Photo":"https://media.api-sports.io/football/players/105.png"},"Statistics":[{"Games":{"Minutes":21,"Number":2,"Position":"D","Rating":"6.2","Captain":false,"Substitute":true},"Offsides":null,"Shots":{"Total":null,"On":null},"Goals":{"Total":null,"Conceded":0,"Assists":null,"Saves":null},"Passes":{"Total":13,"Key":null,"Accuracy":"12"},"Tackles":{"Total":null,"Blocks":null,"Interceptions":null},"Duels":{"Total":3,"Won":null},"Dribbles":{"Attempts":null,"Success":null,"Past":null},"Fouls":{"Drawn":null,"Committed":null},"Cards":{"Yellow":0,"Red":0},"Penalty":{"Won":null,"Commited":null,"Scored":0,"Missed":0,"Saved":null}}]},{"Player":{"Id":163039,"Name":"Chrislain Matsima","Photo":"https://media.api-sports.io/football/players/163039.png"},"Statistics":[{"Games":{"Minutes":null,"Number":34,"Position":"D","Rating":null,"Captain":false,"Substitute":true},"Offsides":null,"Shots":{"Total":null,"On":null},"Goals":{"Total":null,"Conceded":0,"Assists":null,"Saves":null},"Passes":{"Total":null,"Key":null,"Accuracy":null},"Tackles":{"Total":null,"Blocks":null,"Interceptions":null},"Duels":{"Total":null,"Won":null},"Dribbles":{"Attempts":null,"Success":null,"Past":null},"Fouls":{"Drawn":null,"Committed":null},"Cards":{"Yellow":0,"Red":0},"Penalty":{"Won":null,"Commited":null,"Scored":0,"Missed":0,"Saved":null}}]},{"Player":{"Id":162887,"Name":"Enzo Millot","Photo":"https://media.api-sports.io/football/players/162887.png"},"Statistics":[{"Games":{"Minutes":14,"Number":38,"Position":"F","Rating":"6.9","Captain":false,"Substitute":true},"Offsides":null,"Shots":{"Total":2,"On":1},"Goals":{"Total":null,"Conceded":0,"Assists":null,"Saves":null},"Passes":{"Total":5,"Key":null,"Accuracy":"3"},"Tackles":{"Total":2,"Blocks":null,"Interceptions":1},"Duels":{"Total":7,"Won":4},"Dribbles":{"Attempts":2,"Success":null,"Past":null},"Fouls":{"Drawn":1,"Committed":null},"Cards":{"Yellow":0,"Red":0},"Penalty":{"Won":null,"Commited":null,"Scored":0,"Missed":0,"Saved":null}}]},{"Player":{"Id":162991,"Name":"Eliot Matazo","Photo":"https://media.api-sports.io/football/players/162991.png"},"Statistics":[{"Games":{"Minutes":null,"Number":36,"Position":"M","Rating":null,"Captain":false,"Substitute":true},"Offsides":null,"Shots":{"Total":null,"On":null},"Goals":{"Total":null,"Conceded":0,"Assists":null,"Saves":null},"Passes":{"Total":null,"Key":null,"Accuracy":null},"Tackles":{"Total":null,"Blocks":null,"Interceptions":null},"Duels":{"Total":null,"Won":null},"Dribbles":{"Attempts":null,"Success":null,"Past":null},"Fouls":{"Drawn":null,"Committed":null},"Cards":{"Yellow":0,"Red":0},"Penalty":{"Won":null,"Commited":null,"Scored":0,"Missed":0,"Saved":null}}]},{"Player":{"Id":121,"Name":"Stevan Joveti\u0107","Photo":"https://media.api-sports.io/football/players/121.png"},"Statistics":[{"Games":{"Minutes":32,"Number":10,"Position":"F","Rating":"6.9","Captain":false,"Substitute":true},"Offsides":null,"Shots":{"Total":null,"On":null},"Goals":{"Total":null,"Conceded":0,"Assists":null,"Saves":null},"Passes":{"Total":21,"Key":1,"Accuracy":"16"},"Tackles":{"Total":null,"Blocks":null,"Interceptions":null},"Duels":{"Total":7,"Won":4},"Dribbles":{"Attempts":3,"Success":2,"Past":null},"Fouls":{"Drawn":1,"Committed":1},"Cards":{"Yellow":0,"Red":0},"Penalty":{"Won":null,"Commited":null,"Scored":0,"Missed":0,"Saved":null}}]},{"Player":{"Id":123,"Name":"Pietro Pellegri","Photo":"https://media.api-sports.io/football/players/123.png"},"Statistics":[{"Games":{"Minutes":31,"Number":19,"Position":"F","Rating":"6.7","Captain":false,"Substitute":true},"Offsides":null,"Shots":{"Total":1,"On":null},"Goals":{"Total":null,"Conceded":0,"Assists":null,"Saves":null},"Passes":{"Total":2,"Key":null,"Accuracy":null},"Tackles":{"Total":null,"Blocks":null,"Interceptions":null},"Duels":{"Total":2,"Won":1},"Dribbles":{"Attempts":null,"Success":null,"Past":null},"Fouls":{"Drawn":1,"Committed":null},"Cards":{"Yellow":0,"Red":0},"Penalty":{"Won":null,"Commited":null,"Scored":0,"Missed":0,"Saved":null}}]},{"Player":{"Id":120,"Name":"Willem Geubbels","Photo":"https://media.api-sports.io/football/players/120.png"},"Statistics":[{"Games":{"Minutes":null,"Number":13,"Position":"F","Rating":null,"Captain":false,"Substitute":true},"Offsides":null,"Shots":{"Total":null,"On":null},"Goals":{"Total":null,"Conceded":0,"Assists":null,"Saves":null},"Passes":{"Total":null,"Key":null,"Accuracy":null},"Tackles":{"Total":null,"Blocks":null,"Interceptions":null},"Duels":{"Total":null,"Won":null},"Dribbles":{"Attempts":null,"Success":null,"Past":null},"Fouls":{"Drawn":null,"Committed":null},"Cards":{"Yellow":0,"Red":0},"Penalty":{"Won":null,"Commited":null,"Scored":0,"Missed":0,"Saved":null}}]}]}]}